luah-1.1.0.dist-info/METADATA
luah-1.1.0.dist-info/WHEEL
luah-1.1.0.dist-info/entry_points.txt
luah-1.1.0.dist-info/licenses/LICENSE
luah/LibCore.pyi
luah/__init__.py
luah/__main__.py
luah/LibCore.pyd
luah-1.1.0.dist-info/RECORD
