Metadata-Version: 2.3
Name: luah
Version: 1.1.0
Classifier: Development Status :: 5 - Production/Stable
Classifier: Framework :: Robot Framework
Classifier: Framework :: Robot Framework :: Library
Classifier: Operating System :: OS Independent
Classifier: Programming Language :: Python :: 3
Classifier: Programming Language :: Rust
Classifier: Programming Language :: Python :: Implementation :: CPython
Classifier: Programming Language :: Python :: Implementation :: PyPy
License-File: LICENSE
Summary: HydroRoll Lua Impl Project
Keywords: hydroroll,lua,pyo3
Home-Page: https://hydroroll.team/
Author: HsiangNianian
Author-email: HsiangNianian <leader@hydroroll.team>
License: AGPL-3.0
Requires-Python: >=3.9
Project-URL: homepage, https://hydroroll.team/
Project-URL: repository, https://github.com/HydroRoll-Team/luah
Project-URL: documentation, https://luah.hydroroll.team/
